example/test_poc.py
frameflow/__init__.py
frameflow/__init__.pyi
frameflow/py.typed
frameflow/typing.pyi
frameflow-0.1.0.dist-info/licenses/LICENSE
mypy_frameflow/__init__.py
mypy_frameflow/plugin.py
frameflow-0.1.0.dist-info/METADATA
frameflow-0.1.0.dist-info/WHEEL
frameflow-0.1.0.dist-info/entry_points.txt
frameflow-0.1.0.dist-info/top_level.txt
frameflow-0.1.0.dist-info/RECORD
