Metadata-Version: 2.4
Name: frameflow
Version: 0.1.0
Summary: Column-aware pandas typing via a mypy plugin
Author: Marcel Qayoom Taylor
License: MIT License
Project-URL: Homepage, https://github.com/marcel-qayoom-taylor/FrameFlow
Project-URL: Repository, https://github.com/marcel-qayoom-taylor/FrameFlow
Project-URL: Issues, https://github.com/marcel-qayoom-taylor/FrameFlow/issues
Classifier: Development Status :: 3 - Alpha
Classifier: Intended Audience :: Developers
Classifier: License :: OSI Approved :: MIT License
Classifier: Programming Language :: Python
Classifier: Programming Language :: Python :: 3
Classifier: Programming Language :: Python :: 3 :: Only
Classifier: Programming Language :: Python :: 3.10
Classifier: Programming Language :: Python :: 3.11
Classifier: Programming Language :: Python :: 3.12
Classifier: Programming Language :: Python :: 3.13
Classifier: Typing :: Typed
Requires-Python: >=3.10
License-File: LICENSE
Provides-Extra: pandas
Requires-Dist: pandas>=2.1; extra == "pandas"
Requires-Dist: pandas-stubs>=2.3.2.250926; extra == "pandas"
Provides-Extra: pandera
Requires-Dist: pandera>=0.26.1; extra == "pandera"
Provides-Extra: all
Requires-Dist: pandas>=2.1; extra == "all"
Requires-Dist: pandas-stubs>=2.3.2.250926; extra == "all"
Requires-Dist: pandera>=0.26.1; extra == "all"
Provides-Extra: dev
Requires-Dist: ruff>=0.6.9; extra == "dev"
Requires-Dist: pre-commit>=3.7.1; extra == "dev"
Requires-Dist: mypy>=1.10; extra == "dev"
Dynamic: license-file
